tempus_dominus/__init__.py
tempus_dominus/widgets.py
tempus_dominus/templates/tempus_dominus/widget.html
tests/__init__.py
tests/forms.py
tests/requirements.txt
tests/settings.py
tests/test_forms.py
tests/test_widgets.py
django_tempus_dominus-5.1.2.17.dist-info/LICENSE
django_tempus_dominus-5.1.2.17.dist-info/METADATA
django_tempus_dominus-5.1.2.17.dist-info/WHEEL
django_tempus_dominus-5.1.2.17.dist-info/top_level.txt
django_tempus_dominus-5.1.2.17.dist-info/RECORD
